leetcode_runner/__init__.py
leetcode_runner/cli.py
leetcode_runner/fetcher.py
leetcode_runner/generator.py
leetcode_runner/log.py
leetcode_runner/models.py
leetcode_runner/runner.py
leetcode_runner-0.0.4.dist-info/entry_points.txt
leetcode_runner-0.0.4.dist-info/LICENSE.md
leetcode_runner-0.0.4.dist-info/WHEEL
leetcode_runner-0.0.4.dist-info/METADATA
leetcode_runner-0.0.4.dist-info/RECORD
