Metadata-Version: 2.1
Name: leetcode-runner
Version: 0.0.4
Summary: LeetCode solutions runner
Home-page: https://pypi.org/project/leetcode_runner
License: MIT
Keywords: leetcode,runner
Author: fbjorn
Author-email: denis@fbjorn.cc
Requires-Python: >=3.9,<4.0
Classifier: License :: OSI Approved :: MIT License
Classifier: Natural Language :: English
Classifier: Operating System :: OS Independent
Classifier: Programming Language :: Python
Classifier: Programming Language :: Python :: 3
Classifier: Programming Language :: Python :: 3.10
Classifier: Programming Language :: Python :: 3.9
Requires-Dist: beautifulsoup4 (>=4.11.1,<5.0.0)
Requires-Dist: colorama (>=0.4.4,<0.5.0)
Requires-Dist: gql[requests] (>=3.4.0,<4.0.0)
Requires-Dist: pydantic (>=1.10.2,<2.0.0)
Requires-Dist: termcolor (>=1.1.0,<2.0.0)
Requires-Dist: typer (>=0.6.1,<0.7.0)
Project-URL: Documentation, https://github.com/fbjorn/leetcode-runner
Project-URL: Repository, https://github.com/fbjorn/leetcode-runner
